prosperity2bt/__init__.py
prosperity2bt/__main__.py
prosperity2bt/data.py
prosperity2bt/datamodel.py
prosperity2bt/file_reader.py
prosperity2bt/models.py
prosperity2bt/runner.py
prosperity2bt/resources/__init__.py
prosperity2bt/resources/round0/__init__.py
prosperity2bt/resources/round0/prices_round_0_day_-2.csv
prosperity2bt/resources/round0/trades_round_0_day_-2_nn.csv
prosperity2bt/resources/round1/__init__.py
prosperity2bt/resources/round1/prices_round_1_day_-1.csv
prosperity2bt/resources/round1/prices_round_1_day_-2.csv
prosperity2bt/resources/round1/prices_round_1_day_0.csv
prosperity2bt/resources/round1/trades_round_1_day_-1_nn.csv
prosperity2bt/resources/round1/trades_round_1_day_-1_wn.csv
prosperity2bt/resources/round1/trades_round_1_day_-2_nn.csv
prosperity2bt/resources/round1/trades_round_1_day_-2_wn.csv
prosperity2bt/resources/round1/trades_round_1_day_0_nn.csv
prosperity2bt/resources/round1/trades_round_1_day_0_wn.csv
prosperity2bt/resources/round3/__init__.py
prosperity2bt/resources/round3/prices_round_3_day_0.csv
prosperity2bt/resources/round3/prices_round_3_day_1.csv
prosperity2bt/resources/round3/prices_round_3_day_2.csv
prosperity2bt/resources/round3/trades_round_3_day_0_nn.csv
prosperity2bt/resources/round3/trades_round_3_day_0_wn.csv
prosperity2bt/resources/round3/trades_round_3_day_1_nn.csv
prosperity2bt/resources/round3/trades_round_3_day_1_wn.csv
prosperity2bt/resources/round3/trades_round_3_day_2_nn.csv
prosperity2bt/resources/round3/trades_round_3_day_2_wn.csv
prosperity2bt/resources/round4/__init__.py
prosperity2bt/resources/round4/prices_round_4_day_1.csv
prosperity2bt/resources/round4/prices_round_4_day_2.csv
prosperity2bt/resources/round4/prices_round_4_day_3.csv
prosperity2bt/resources/round4/trades_round_4_day_1_nn.csv
prosperity2bt/resources/round4/trades_round_4_day_1_wn.csv
prosperity2bt/resources/round4/trades_round_4_day_2_nn.csv
prosperity2bt/resources/round4/trades_round_4_day_2_wn.csv
prosperity2bt-0.9.4.dist-info/LICENSE
prosperity2bt-0.9.4.dist-info/METADATA
prosperity2bt-0.9.4.dist-info/WHEEL
prosperity2bt-0.9.4.dist-info/entry_points.txt
prosperity2bt-0.9.4.dist-info/top_level.txt
prosperity2bt-0.9.4.dist-info/RECORD
